paapi_models/__init__.py
paapi_models/adapters.py
paapi_models/models.py
paapi_models-0.1.1.dist-info/WHEEL
paapi_models-0.1.1.dist-info/METADATA
paapi_models-0.1.1.dist-info/RECORD
